synbols/__init__.py
synbols/data_io.py
synbols/drawing.py
synbols/generate.py
synbols/predefined_datasets.py
synbols/utils.py
synbols/visualization.py
synbols/entrypoints/__init__.py
synbols/entrypoints/generate_datasets.py
synbols/entrypoints/jupyter.py
synbols/entrypoints/run_docker.py
synbols/entrypoints/view_dataset.py
synbols/fonts/__init__.py
synbols/fonts/blacklist/__init__.py
synbols/fonts/blacklist/blacklist_english.tsv
synbols/fonts/blacklist/font_clusters_english.json
synbols/stratified_splits/__init__.py
synbols-1.0.2.dist-info/METADATA
synbols-1.0.2.dist-info/WHEEL
synbols-1.0.2.dist-info/entry_points.txt
synbols-1.0.2.dist-info/top_level.txt
synbols-1.0.2.dist-info/RECORD
