Metadata-Version: 2.1
Name: synbols
Version: 1.0.2
Summary: Synbols: Probing Learning Algorithms with Synthetic Datasets
Home-page: https://github.com/ElementAI/synbols
Author: Alexandre Lacoste, Pau Rodriguez, Frederic Branchaud-Charron, Parmida Atighehchian, Massimo Caccia, Issam Hadj Laradji, Alexandre Drouin, Matt Craddock, Laurent Charlin, David Vazquez
Author-email: allac@elementai.com
License: UNKNOWN
Platform: UNKNOWN
Classifier: Development Status :: 5 - Production/Stable
Classifier: Programming Language :: Python :: 3
Classifier: License :: OSI Approved :: Apache Software License
Classifier: Operating System :: Unix
Classifier: Intended Audience :: Science/Research
Classifier: Topic :: Scientific/Engineering :: Artificial Intelligence
Requires-Python: >=3.6
Requires-Dist: h5py
